{"1":{"name":"Annie","key":6},"2":{"name":"Olaf","key":84},"3":{"name":"Galio","key":31},"4":{"name":"Twisted Fate","key":127},"5":{"name":"Xin Zhao","key":143},"6":{"name":"Urgot","key":130},"7":{"name":"LeBlanc","key":61},"8":{"name":"Vladimir","key":138},"9":{"name":"Fiddlesticks","key":28},"10":{"name":"Kayle","key":54},"11":{"name":"Master Yi","key":72},"12":{"name":"Alistar","key":3},"13":{"name":"Ryze","key":100},"14":{"name":"Sion","key":110},"15":{"name":"Sivir","key":111},"16":{"name":"Soraka","key":114},"17":{"name":"Teemo","key":122},"18":{"name":"Tristana","key":124},"19":{"name":"Warwick","key":140},"20":{"name":"Nunu & Willump","key":83},"21":{"name":"Miss Fortune","key":73},"22":{"name":"Ashe","key":8},"23":{"name":"Tryndamere","key":126},"24":{"name":"Jax","key":44},"25":{"name":"Morgana","key":76},"26":{"name":"Zilean","key":151},"27":{"name":"Singed","key":109},"28":{"name":"Evelynn","key":26},"29":{"name":"Twitch","key":128},"30":{"name":"Karthus","key":51},"31":{"name":"Cho'Gath","key":18},"32":{"name":"Amumu","key":4},"33":{"name":"Rammus","key":93},"34":{"name":"Anivia","key":5},"35":{"name":"Shaco","key":106},"36":{"name":"Dr. Mundo","key":23},"37":{"name":"Sona","key":113},"38":{"name":"Kassadin","key":52},"39":{"name":"Irelia","key":40},"40":{"name":"Janna","key":42},"41":{"name":"Gangplank","key":32},"42":{"name":"Corki","key":19},"43":{"name":"Karma","key":50},"44":{"name":"Taric","key":121},"45":{"name":"Veigar","key":133},"48":{"name":"Trundle","key":125},"50":{"name":"Swain","key":115},"51":{"name":"Caitlyn","key":15},"53":{"name":"Blitzcrank","key":12},"54":{"name":"Malphite","key":69},"55":{"name":"Katarina","key":53},"56":{"name":"Nocturne","key":82},"57":{"name":"Maokai","key":71},"58":{"name":"Renekton","key":96},"59":{"name":"Jarvan IV","key":43},"60":{"name":"Elise","key":25},"61":{"name":"Orianna","key":85},"62":{"name":"Wukong","key":74},"63":{"name":"Brand","key":13},"64":{"name":"Lee Sin","key":62},"67":{"name":"Vayne","key":132},"68":{"name":"Rumble","key":99},"69":{"name":"Cassiopeia","key":17},"72":{"name":"Skarner","key":112},"74":{"name":"Heimerdinger","key":38},"75":{"name":"Nasus","key":78},"76":{"name":"Nidalee","key":81},"77":{"name":"Udyr","key":129},"78":{"name":"Poppy","key":88},"79":{"name":"Gragas","key":35},"80":{"name":"Pantheon","key":87},"81":{"name":"Ezreal","key":27},"82":{"name":"Mordekaiser","key":75},"83":{"name":"Yorick","key":146},"84":{"name":"Akali","key":2},"85":{"name":"Kennen","key":56},"86":{"name":"Garen","key":33},"89":{"name":"Leona","key":63},"90":{"name":"Malzahar","key":70},"91":{"name":"Talon","key":120},"92":{"name":"Riven","key":98},"96":{"name":"Kog'Maw","key":60},"98":{"name":"Shen","key":107},"99":{"name":"Lux","key":68},"101":{"name":"Xerath","key":142},"102":{"name":"Shyvana","key":108},"103":{"name":"Ahri","key":1},"104":{"name":"Graves","key":36},"105":{"name":"Fizz","key":30},"106":{"name":"Volibear","key":139},"107":{"name":"Rengar","key":97},"110":{"name":"Varus","key":131},"111":{"name":"Nautilus","key":79},"112":{"name":"Viktor","key":137},"113":{"name":"Sejuani","key":102},"114":{"name":"Fiora","key":29},"115":{"name":"Ziggs","key":150},"117":{"name":"Lulu","key":67},"119":{"name":"Draven","key":22},"120":{"name":"Hecarim","key":37},"121":{"name":"Kha'Zix","key":57},"122":{"name":"Darius","key":20},"126":{"name":"Jayce","key":45},"127":{"name":"Lissandra","key":65},"131":{"name":"Diana","key":21},"133":{"name":"Quinn","key":91},"134":{"name":"Syndra","key":117},"136":{"name":"Aurelion Sol","key":9},"141":{"name":"Kayn","key":55},"142":{"name":"Zoe","key":152},"143":{"name":"Zyra","key":153},"145":{"name":"Kai'Sa","key":48},"147":{"name":"Seraphine","key":104},"150":{"name":"Gnar","key":34},"154":{"name":"Zac","key":148},"157":{"name":"Yasuo","key":144},"161":{"name":"Vel'Koz","key":134},"163":{"name":"Taliyah","key":119},"164":{"name":"Camille","key":16},"201":{"name":"Braum","key":14},"202":{"name":"Jhin","key":46},"203":{"name":"Kindred","key":58},"222":{"name":"Jinx","key":47},"223":{"name":"Tahm Kench","key":118},"234":{"name":"Viego","key":136},"235":{"name":"Senna","key":103},"236":{"name":"Lucian","key":66},"238":{"name":"Zed","key":149},"240":{"name":"Kled","key":59},"245":{"name":"Ekko","key":24},"246":{"name":"Qiyana","key":90},"254":{"name":"Vi","key":135},"266":{"name":"Aatrox","key":0},"267":{"name":"Nami","key":77},"268":{"name":"Azir","key":10},"350":{"name":"Yuumi","key":147},"360":{"name":"Samira","key":101},"412":{"name":"Thresh","key":123},"420":{"name":"Illaoi","key":39},"421":{"name":"Rek'Sai","key":94},"427":{"name":"Ivern","key":41},"429":{"name":"Kalista","key":49},"432":{"name":"Bard","key":11},"497":{"name":"Rakan","key":92},"498":{"name":"Xayah","key":141},"516":{"name":"Ornn","key":86},"517":{"name":"Sylas","key":116},"518":{"name":"Neeko","key":80},"523":{"name":"Aphelios","key":7},"526":{"name":"Rell","key":95},"555":{"name":"Pyke","key":89},"777":{"name":"Yone","key":145},"875":{"name":"Sett","key":105},"876":{"name":"Lillia","key":64}}